{
    "2022-01-11": [
        {
            "kind": "CL",
            "n": 0,
            "title": "Welcome to COMP110",
            "date": "2022-01-11",
            "deadline": "None",
            "links": {
                "In-person Hamilton 100": "",
                "Quarantine Stream": "https://youtu.be/TnFg2hUteSM",
                "Slides": "/static/slides/cl00-welcome.pdf"
            }
        },
        {
            "kind": "LS",
            "n": 0,
            "title": "Syllabus and Support - Due Weds 1/12 @ 11:59pm",
            "date": "2022-01-11",
            "deadline": "2022-01-12",
            "links": {
                "1. Read the Syllabus": "/resources/syllabus.html",
                "2. Read Support Resources": "/support",
                "3. Complete Lesson 00 Responses on Gradescope": "https://www.gradescope.com/"
            }
        },
        {
            "kind": "EX",
            "n": 0,
            "title": "Hello World - Due Mon 1/17 @ 11:59pm",
            "date": "2022-01-11",
            "deadline": "2022-01-17",
            "links": {
                "Software Setup (1/3)": "/resources/setup/os-update.html",
                "Software Setup (2/3)": "/resources/setup/software.html",
                "Software Setup (3/3)": "/resources/setup/workspace.html",
                "EX00 - Hello, World": "/exercises/ex00_hello_world.html"
            }
        }
    ],
    "2022-01-12": [],
    "2022-01-13": [
        {
            "kind": "CL",
            "n": 1,
            "title": "Async Day - Submit Gradescope Responses by 1/14",
            "date": "2022-01-13",
            "deadline": "None",
            "links": {
                "Watch Lessons 01 - 03 Below": ""
            }
        },
        {
            "kind": "LS",
            "n": 1,
            "title": "Computer Systems - Processes, Shells, Kernels, and Hardware",
            "date": "2022-01-13",
            "deadline": "2022-01-14",
            "links": {
                "Watch Lesson": "https://youtu.be/LB9wVRYF9tA"
            }
        },
        {
            "kind": "LS",
            "n": 2,
            "title": "Programs, Languages, and Interpreters",
            "date": "2022-01-13",
            "deadline": "2022-01-14",
            "links": {
                "Watch Lesson": "https://youtu.be/aMjlaAWp-sw"
            }
        },
        {
            "kind": "LS",
            "n": 3,
            "title": "VSCode Walkthrough",
            "date": "2022-01-13",
            "deadline": "2022-01-14",
            "links": {
                "Watch Lesson": "https://youtu.be/CA5-9qXNSqw"
            }
        },
        {
            "kind": "HW",
            "n": 0,
            "title": "Homework: Lessons 04 & 05 Due 1/17",
            "date": "2022-01-13",
            "deadline": "None",
            "links": {
                "Reat Lessons and Submit Responses on Gradescope": "https://gradescope.com"
            }
        },
        {
            "kind": "LS",
            "n": 4,
            "title": "Objects and Data Types",
            "date": "2022-01-13",
            "deadline": "2022-01-17",
            "links": {
                "Read Lesson": "/lessons/objects-data-types.html"
            }
        },
        {
            "kind": "LS",
            "n": 5,
            "title": "Expressions",
            "date": "2022-01-13",
            "deadline": "2022-01-17",
            "links": {
                "Read Lesson": "/lessons/expressions.html"
            }
        }
    ],
    "2022-01-14": [],
    "2022-01-15": [],
    "2022-01-16": [],
    "2022-01-17": [],
    "2022-01-18": [
        {
            "kind": "CL",
            "n": 2,
            "title": "Async Day - Submit Gradescope Responses by 1/19",
            "date": "2022-01-18",
            "deadline": "None",
            "links": {
                "Watch Lessons Below": ""
            }
        },
        {
            "kind": "LS",
            "n": 6,
            "title": "Variables and User Input",
            "date": "2022-01-18",
            "deadline": "2022-01-19",
            "links": {
                "Watch Lesson": "https://youtu.be/wXoUw0scEsI"
            }
        },
        {
            "kind": "LS",
            "n": 7,
            "title": "Environment Diagrams",
            "date": "2022-01-18",
            "deadline": "2022-01-19",
            "links": {
                "Watch Lesson": "https://youtu.be/Vfmuwx3vYKg"
            }
        },
        {
            "kind": "LS",
            "n": 8,
            "title": "Conditional if-else Statements",
            "date": "2022-01-18",
            "deadline": "2022-01-19",
            "links": {
                "Watch Lesson": "https://youtu.be/JP5oFPHw5zc"
            }
        },
        {
            "kind": "EX",
            "n": 1,
            "title": "Chardle - Input, Variables, and Conditionals - Due Mon 1/24 @ 11:59pm",
            "date": "2022-01-18",
            "deadline": "2022-01-24",
            "links": {
                "EX01 - Chardle": "/exercises/ex01.html"
            }
        }
    ],
    "2022-01-19": [],
    "2022-01-20": [
        {
            "kind": "QZ",
            "n": 0,
            "title": "Quiz 0",
            "date": "2022-01-20",
            "deadline": "2022-01-20",
            "links": {
                "What to expect and how to prepare?": "/resources/quiz-expectations.html",
                "Review Question #1 - Numerical Expression": "https://youtu.be/ISP-9wkrlyM",
                "Review Question #2 - Rational Expressions": "https://youtu.be/g8_OERDtJ8c",
                "Review Question #3 - if-then-else Statements": "https://youtu.be/ruWo2zP9p4U",
                "More Practice Questions": "/resources/practice/sp22/quiz0-worksheet.html",
                "Covered Topics: Syllabus, Resources Page, Lessons 4 - 8": ""
            }
        }
    ],
    "2022-01-21": [],
    "2022-01-22": [],
    "2022-01-23": [],
    "2022-01-24": [],
    "2022-01-25": [
        {
            "kind": "CL",
            "n": 4,
            "title": "Async Day - Submit Gradescope Responses by 1/26",
            "date": "2022-01-25",
            "deadline": "None",
            "links": {
                "Watch Lessons 09 - 10 Below": ""
            }
        },
        {
            "kind": "LS",
            "n": 9,
            "title": "while Loop Statements",
            "date": "2022-01-25",
            "deadline": "2022-01-26",
            "links": {
                "Watch Lesson": "https://www.youtube.com/watch?v=pvpgvYlyfUU"
            }
        },
        {
            "kind": "LS",
            "n": 10,
            "title": "Boolean Operators: and, or, not",
            "date": "2022-01-25",
            "deadline": "2022-01-26",
            "links": {
                "Watch Lesson": "https://youtu.be/HYq9Zoigoc4"
            }
        },
        {
            "kind": "LS",
            "n": 11,
            "title": "EX02 Background Lesson: Advanced String Concepts (Due 1/31 at 11:59pm)",
            "date": "2022-01-25",
            "deadline": "2022-01-31",
            "links": {
                "Read Background Lesson": "/lessons/strings.html"
            }
        },
        {
            "kind": "EX",
            "n": 2,
            "title": "One-shot Wordle",
            "date": "2022-01-25",
            "deadline": "2022-01-31",
            "links": {
                "EX02 - One Shot Wordle": "/exercises/ex02.html"
            }
        }
    ],
    "2022-01-26": [],
    "2022-01-27": [
        {
            "kind": "CL",
            "n": 5,
            "title": "In-Person: Practice with Control Flow",
            "date": "2022-01-27",
            "deadline": "None",
            "links": {
                "Quarantine YouTube Stream": "https://youtu.be/2Uw5yVUXx0Y",
                "Slides": "/static/slides/cl05-control-flow-practice.pdf"
            }
        }
    ],
    "2022-01-28": [],
    "2022-01-29": [],
    "2022-01-30": [],
    "2022-01-31": [],
    "2022-02-01": [
        {
            "kind": "CL",
            "n": 6,
            "title": "Async Day - Submit Gradescope Responses by 2/2",
            "date": "2022-02-01",
            "deadline": "None",
            "links": {
                "Watch Lessons 11 - 13 Below": ""
            }
        },
        {
            "kind": "LS",
            "n": 12,
            "title": "Introducing Functions",
            "date": "2022-02-01",
            "deadline": "2022-02-02",
            "links": {
                "Watch Lesson": "https://youtu.be/UheQNnstJE8"
            }
        },
        {
            "kind": "LS",
            "n": 13,
            "title": "Function Syntax",
            "date": "2022-02-01",
            "deadline": "2022-02-02",
            "links": {
                "Watch Lesson": "https://youtu.be/ihpN4LOqx8s"
            }
        },
        {
            "kind": "LS",
            "n": 14,
            "title": "Function Semantics",
            "date": "2022-02-01",
            "deadline": "2022-02-02",
            "links": {
                "Watch Lesson": "https://youtu.be/_swT3gKjDVg"
            }
        },
        {
            "kind": "EX",
            "n": 3,
            "title": "Structured Wordle",
            "date": "2022-02-01",
            "deadline": "2022-02-07",
            "links": {
                "EX03 - Structured Wordle": "/exercises/ex03.html"
            }
        }
    ],
    "2022-02-02": [],
    "2022-02-03": [
        {
            "kind": "CL",
            "n": 7,
            "title": "In-Person: Practice with Functions",
            "date": "2022-02-03",
            "deadline": "None",
            "links": {
                "Quarantine YouTube Stream": "https://youtu.be/EiFkk_KCkyA",
                "Slides": "/static/slides/cl07-function-practice.pdf"
            }
        }
    ],
    "2022-02-04": [],
    "2022-02-05": [],
    "2022-02-06": [],
    "2022-02-07": [],
    "2022-02-08": [
        {
            "kind": "CL",
            "n": 8,
            "title": "Async Day - Submit Gradescope Responses by 2/9",
            "date": "2022-02-08",
            "deadline": "None",
            "links": {
                "Watch Lessons 14": ""
            }
        },
        {
            "kind": "LS",
            "n": 15,
            "title": "Lists",
            "date": "2022-02-08",
            "deadline": "2022-02-09",
            "links": {
                "Watch Lesson": "https://www.youtube.com/watch?v=uGsgE_EKI4U"
            }
        },
        {
            "kind": "RV",
            "n": 0,
            "title": "Review Session for Quiz 1",
            "date": "2022-02-08",
            "deadline": "None",
            "links": {
                "Recording Passcode: 8@e.caM#": "https://unc.zoom.us/rec/share/tiJrKXEoIlLRQWVoOvSap_Zho4gbQKVZBuOZV-UKmOvyP7vSLAfbb8Wm4k9DamnL.WMRkCWG1u__bPZZJ?startTime=1644363199000",
                "Slides": "https://docs.google.com/presentation/d/1qb3dbSPHiWQMkJA_z-Yw40wTxGdDoSEvjcparFZ6OI8/edit?usp=sharing"
            }
        }
    ],
    "2022-02-09": [],
    "2022-02-10": [
        {
            "kind": "QZ",
            "n": 1,
            "title": "Quiz 1",
            "date": "2022-02-10",
            "deadline": "2022-02-10",
            "links": {
                "Practice Questions": "/resources/practice/sp22/quiz1-worksheet.html",
                "Practice Diagram #1": "https://www.youtube.com/watch?v=Mz7uP3Gyj8U",
                "Practice Diagram #2": "https://www.youtube.com/watch?v=7pp8uJjpGKQ"
            }
        },
        {
            "kind": "EX",
            "n": 4,
            "title": "Turtle Art - Due Weds Feb 16",
            "date": "2022-02-10",
            "deadline": "2022-02-16",
            "links": {
                "Write-up": "/exercises/ex04.html"
            }
        }
    ],
    "2022-02-11": [],
    "2022-02-12": [],
    "2022-02-13": [],
    "2022-02-14": [],
    "2022-02-15": [
        {
            "kind": "CL",
            "n": 10,
            "title": "Async Day - Submit Gradescope Responses by 2/15",
            "date": "2022-02-15",
            "deadline": "None",
            "links": {
                "Read Lesson 16 and Watch Lessons 17, 18": ""
            }
        },
        {
            "kind": "LS",
            "n": 16,
            "title": "Scopes, Globals, and Constants",
            "date": "2022-02-15",
            "deadline": "2022-02-16",
            "links": {
                "Read Lesson": "/lessons/scopes-constants-globals.html"
            }
        },
        {
            "kind": "LS",
            "n": 17,
            "title": "Unit Testing",
            "date": "2022-02-15",
            "deadline": "2022-02-16",
            "links": {
                "Watch Lesson": "https://www.youtube.com/watch?v=VAdJybtia-4"
            }
        },
        {
            "kind": "LS",
            "n": 18,
            "title": "for..in Loops",
            "date": "2022-02-15",
            "deadline": "2022-02-16",
            "links": {
                "Watch Lesson": "https://www.youtube.com/watch?v=YPfFCD_RGK8"
            }
        }
    ],
    "2022-02-16": [],
    "2022-02-17": [
        {
            "kind": "CL",
            "n": 11,
            "title": "In-Person: Practice with Lists and Scope",
            "date": "2022-02-17",
            "deadline": "None",
            "links": {
                "Complete Required Course Survey by Fri, Feb 18": "https://forms.gle/T4ryvAd6TizBNmf2A",
                "Quarantine Stream": "https://youtu.be/pO8R5USJb_Q",
                "Slides": "/static/slides/cl11-list-practice.pdf"
            }
        },
        {
            "kind": "EX",
            "n": 5,
            "title": "List Algorithms and Unit Tests - Due Weds Feb 23",
            "date": "2022-02-17",
            "deadline": "2022-02-23",
            "links": {
                "Write-up": "/exercises/ex05.html"
            }
        },
        {
            "kind": "RD",
            "n": 0,
            "title": "Reading: Ethical Algorithms Chapter - Due Mar 11",
            "date": "2022-02-17",
            "deadline": "2022-03-11",
            "links": {
                "See Gradescope": "https://www.gradescope.com"
            }
        }
    ],
    "2022-02-18": [],
    "2022-02-19": [],
    "2022-02-20": [],
    "2022-02-21": [],
    "2022-02-22": [
        {
            "kind": "LS",
            "n": 19,
            "title": "Dictionaries",
            "date": "2022-02-22",
            "deadline": "2022-02-23",
            "links": {
                "Watch Lesson": "https://www.youtube.com/watch?v=2B8Nh3pJEFE"
            }
        }
    ],
    "2022-02-23": [],
    "2022-02-24": [
        {
            "kind": "CL",
            "n": 13,
            "title": "In-Person: Practice with Dictionaries",
            "date": "2022-02-24",
            "deadline": "None",
            "links": {
                "Quarantine Stream": "https://youtu.be/xB06srfd70Y",
                "Slides": "/static/slides/cl13-dictionaries-sequences.pdf"
            }
        },
        {
            "kind": "EX",
            "n": 6,
            "title": "Dictionary Utilities - Due Weds Mar 2",
            "date": "2022-02-24",
            "deadline": "2022-03-02",
            "links": {
                "Write-up": "/exercises/ex06.html"
            }
        }
    ],
    "2022-02-25": [],
    "2022-02-26": [],
    "2022-02-27": [],
    "2022-02-28": [],
    "2022-03-01": [
        {
            "kind": "LS",
            "n": 20,
            "title": "importing in Python",
            "date": "2022-03-01",
            "deadline": "2022-03-02",
            "links": {
                "Watch Lesson": "https://www.youtube.com/watch?v=uTc39ZXStP0"
            }
        },
        {
            "kind": "LS",
            "n": 21,
            "title": "Jupyter Notebooks",
            "date": "2022-03-01",
            "deadline": "2022-03-02",
            "links": {
                "Watch Lesson": "https://www.youtube.com/watch?v=HJgX1WWC26A"
            }
        },
        {
            "kind": "RV",
            "n": 1,
            "title": "Review Session for Quiz 1",
            "date": "2022-03-01",
            "deadline": "None",
            "links": {
                "6:30pm in Sitterson 014": ""
            }
        }
    ],
    "2022-03-02": [],
    "2022-03-03": [
        {
            "kind": "QZ",
            "n": 2,
            "title": "Quiz 2",
            "date": "2022-03-03",
            "deadline": "2022-03-03",
            "links": {
                "Practice Questions": "/resources/practice/sp22/quiz2-worksheet.html"
            }
        }
    ],
    "2022-03-04": [],
    "2022-03-05": [],
    "2022-03-06": [],
    "2022-03-07": [],
    "2022-03-08": [
        {
            "kind": "LS",
            "n": 22,
            "title": "Row-orientation vs. Column-orientation Data Structures",
            "date": "2022-03-08",
            "deadline": "2022-03-09",
            "links": {
                "Watch Lesson": "https://www.youtube.com/watch?v=s5UkpdxbSiM"
            }
        },
        {
            "kind": "LS",
            "n": 23,
            "title": "CSV file Reading",
            "date": "2022-03-08",
            "deadline": "2022-03-09",
            "links": {
                "Watch Lesson": "https://www.youtube.com/watch?v=z4ax7ilh-RY"
            }
        }
    ],
    "2022-03-09": [
        {
            "kind": "EX",
            "n": 7,
            "title": "Data Wrangling - Due Tues 3/22",
            "date": "2022-03-09",
            "deadline": "2022-03-22",
            "links": {
                "Read Write-up": "/exercises/ex07.html"
            }
        }
    ],
    "2022-03-10": [
        {
            "kind": "CL",
            "n": 13,
            "title": "Quantified Shakespeare",
            "date": "2022-03-10",
            "deadline": "None",
            "links": {
                "Quarantine Stream": "https://youtu.be/mTFlO6QjmMU"
            }
        }
    ],
    "2022-03-11": [],
    "2022-03-12": [],
    "2022-03-13": [],
    "2022-03-14": [],
    "2022-03-15": [],
    "2022-03-16": [],
    "2022-03-17": [],
    "2022-03-18": [],
    "2022-03-19": [],
    "2022-03-20": [],
    "2022-03-21": [
        {
            "kind": "RD",
            "n": 1,
            "title": "Weapons of Math Destruction - Due Sun 4/10",
            "date": "2022-03-21",
            "deadline": "2022-04-10",
            "links": {
                "Reading found on Gradescope": "https://gradescope.com"
            }
        }
    ],
    "2022-03-22": [
        {
            "kind": "LS",
            "n": 24,
            "title": "Intro to Object-oriented Programming: Classes, Methods, and __init__",
            "date": "2022-03-22",
            "deadline": "2022-03-23",
            "links": {
                "Watch Lesson": "https://www.youtube.com/watch?v=wBhS8OXtM5Q"
            }
        }
    ],
    "2022-03-23": [
        {
            "kind": "EX",
            "n": 8,
            "title": "Analysis for Continuous Improvement - Due Tues 3/29",
            "date": "2022-03-23",
            "deadline": "2022-03-29",
            "links": {
                "Write-up": "/exercises/ex08.html"
            }
        }
    ],
    "2022-03-24": [
        {
            "kind": "CL",
            "n": 19,
            "title": "Optional Parameters, Union Types, and OOP Practice",
            "date": "2022-03-24",
            "deadline": "None",
            "links": {
                "Quarantine Stream": "https://youtu.be/pZ3m630uGqw"
            }
        }
    ],
    "2022-03-25": [],
    "2022-03-26": [],
    "2022-03-27": [],
    "2022-03-28": [],
    "2022-03-29": [
        {
            "kind": "LS",
            "n": 25,
            "title": "Magic Methods",
            "date": "2022-03-29",
            "deadline": "2022-03-30",
            "links": {
                "Watch Lesson": "https://www.youtube.com/watch?v=yxDIEqm_K6c"
            }
        },
        {
            "kind": "LS",
            "n": 26,
            "title": "Operator Overloading",
            "date": "2022-03-29",
            "deadline": "2022-03-30",
            "links": {
                "Watch Lesson": "https://youtu.be/JJLnGL-cShU"
            }
        },
        {
            "kind": "LS",
            "n": 27,
            "title": "Filtering Column-oriented Data",
            "date": "2022-03-29",
            "deadline": "2022-03-30",
            "links": {
                "Watch Lesson": "https://www.youtube.com/watch?v=_htZ8sB2qe8"
            }
        }
    ],
    "2022-03-30": [
        {
            "kind": "EX",
            "n": 9,
            "title": "Simpy - Due Mon 4/11",
            "date": "2022-03-30",
            "deadline": "2022-04-11",
            "links": {
                "Write-up Posts Weds 3/30": ""
            }
        }
    ],
    "2022-03-31": [
        {
            "kind": "CL",
            "n": 21,
            "title": "Vectorized Operations and OOP Code Writing",
            "date": "2022-03-31",
            "deadline": "None",
            "links": {
                "Quarantine Stream": "https://youtu.be/hNC9VLLNxVU"
            }
        }
    ],
    "2022-04-01": [],
    "2022-04-02": [],
    "2022-04-03": [],
    "2022-04-04": [],
    "2022-04-05": [
        {
            "kind": "LS",
            "n": 28,
            "title": "Intro to Recursion",
            "date": "2022-04-05",
            "deadline": "2022-04-06",
            "links": {
                "Lesson posts 4/5": ""
            }
        },
        {
            "kind": "LS",
            "n": 29,
            "title": "Recursive Data Structures",
            "date": "2022-04-05",
            "deadline": "2022-04-06",
            "links": {
                "Lesson posts 4/5": ""
            }
        }
    ],
    "2022-04-06": [],
    "2022-04-07": [
        {
            "kind": "QZ",
            "n": 3,
            "title": "Quiz 3",
            "date": "2022-04-07",
            "deadline": "2022-04-07",
            "links": {}
        }
    ],
    "2022-04-08": [],
    "2022-04-09": [],
    "2022-04-10": [],
    "2022-04-11": [
        {
            "kind": "RD",
            "n": 2,
            "title": "Gender Shades - Due 4/22",
            "date": "2022-04-11",
            "deadline": "2022-04-22",
            "links": {
                "Reading posts on Gradescope on 4/11": "https://gradescope.com"
            }
        }
    ],
    "2022-04-12": [
        {
            "kind": "LS",
            "n": 30,
            "title": "Intro to NumPy and Pandas",
            "date": "2022-04-12",
            "deadline": "2022-04-13",
            "links": {
                "Lesson posts on Gradescope on 4/9": "https://gradescope.com"
            }
        }
    ],
    "2022-04-13": [
        {
            "kind": "EX",
            "n": 10,
            "title": "Linked List Utils - Due 4/25",
            "date": "2022-04-13",
            "deadline": "2022-04-25",
            "links": {
                "Write-up Posts Wednesday 4/13": ""
            }
        }
    ],
    "2022-04-14": [],
    "2022-04-15": [],
    "2022-04-16": [],
    "2022-04-17": [],
    "2022-04-18": [],
    "2022-04-19": [],
    "2022-04-20": [],
    "2022-04-21": [],
    "2022-04-22": [],
    "2022-04-23": [],
    "2022-04-24": [],
    "2022-04-25": [],
    "2022-04-26": [],
    "2022-04-30": [
        {
            "kind": "FN",
            "n": 0,
            "title": "Final @ 08:00:00",
            "date": "2022-04-30",
            "deadline": "None",
            "links": {}
        }
    ]
}